ext/__init__.py
ext/default.py
ext/gui.py
ext/time.py
kolang/__init__.py
kolang/main.py
kolang/version.txt
kolang/ext/__init__.py
kolang/ext/default.py
kolang/ext/gui.py
kolang/ext/time.py
scripts/__init__.py
scripts/main.py
kolang-1.0.2.dist-info/LICENSE
kolang-1.0.2.dist-info/METADATA
kolang-1.0.2.dist-info/WHEEL
kolang-1.0.2.dist-info/entry_points.txt
kolang-1.0.2.dist-info/top_level.txt
kolang-1.0.2.dist-info/RECORD
